LICENSE
MANIFEST.in
README.md
pyproject.toml
setup.cfg
setup.py
cookie_consent/__init__.py
cookie_consent/apps.py
cookie_consent/cookies.py
cookie_consent/extras.py
cookie_consent/forms.py
cookie_consent/middleware.py
cookie_consent/options.py
cookie_consent/panels.py
cookie_consent/urls.py
cookie_consent/views.py
cookie_consent/locale/de/LC_MESSAGES/django.mo
cookie_consent/locale/de/LC_MESSAGES/django.po
cookie_consent/locale/fr/LC_MESSAGES/django.mo
cookie_consent/locale/fr/LC_MESSAGES/django.po
cookie_consent/locale/nl/LC_MESSAGES/django.mo
cookie_consent/locale/nl/LC_MESSAGES/django.po
cookie_consent/migrations/__init__.py
cookie_consent/migrations/__pycache__/__init__.cpython-311.pyc
cookie_consent/static/cookie_consent/cookie-consent.css
cookie_consent/static/cookie_consent/cookie-consent.js
cookie_consent/static/cookie_consent/img/ga-logo-cookie.svg
cookie_consent/templates/cookie_consent/cookie_modal.html
cookie_consent/templates/cookie_consent/cookie_policy.html
cookie_consent/templatetags/__init__.py
cookie_consent/templatetags/cookies_tags.py
cookie_consent/templatetags/__pycache__/__init__.cpython-311.pyc
cookie_consent/templatetags/__pycache__/cookies_tags.cpython-311.pyc
dc_consent.egg-info/PKG-INFO
dc_consent.egg-info/SOURCES.txt
dc_consent.egg-info/dependency_links.txt
dc_consent.egg-info/requires.txt
dc_consent.egg-info/top_level.txt